pybrush/__init__.py
pybrush/models/__init__.py
pybrush/models/base.py
pybrush/unlearning/__init__.py
pybrush/unlearning/amortized.py
pybrush/unlearning/approximate.py
pybrush/unlearning/certified.py
pybrush/unlearning/exact.py
pybrush/utils/__init__.py
pybrush/utils/data_utils.py
pybrush-0.1.0.dist-info/LICENSE
pybrush-0.1.0.dist-info/METADATA
pybrush-0.1.0.dist-info/WHEEL
pybrush-0.1.0.dist-info/top_level.txt
pybrush-0.1.0.dist-info/RECORD
